seedbank/__init__.py
seedbank/_keys.py
seedbank/_state.py
seedbank/cupy.py
seedbank/numba.py
seedbank/numpy.py
seedbank/stdlib.py
seedbank/tensorflow.py
seedbank/torch.py
seedbank-0.1.3.dist-info/LICENSE.md
seedbank-0.1.3.dist-info/WHEEL
seedbank-0.1.3.dist-info/METADATA
seedbank-0.1.3.dist-info/RECORD
