Metadata-Version: 2.1
Name: seedbank
Version: 0.1.3
Summary: Common infrastructure for initializing random number generators.
Author-email: Michael Ekstrand <michaelekstrand@boisestate.edu>
Requires-Python: >= 3.7
Classifier: License :: OSI Approved :: MIT License
Classifier: Programming Language :: Python :: 3
Classifier: Programming Language :: Python :: 3.7
Classifier: Programming Language :: Python :: 3.8
Classifier: Programming Language :: Python :: 3.9
Classifier: Programming Language :: Python :: 3.10
Classifier: Programming Language :: Python :: 3.11
Classifier: Operating System :: OS Independent
Requires-Dist: numpy >=1.17
Requires-Dist: anyconfig ==0.13.*
Requires-Dist: cupy-cuda11x ; extra == "cuda11x"
Requires-Dist: cupy ; extra == "cupy"
Requires-Dist: flit >=3.2 ; extra == "dev"
Requires-Dist: flake8 ; extra == "dev"
Requires-Dist: ipython ; extra == "dev"
Requires-Dist: sphinx-autobuild ; extra == "dev"
Requires-Dist: invoke ; extra == "dev"
Requires-Dist: conda-lock ; extra == "dev"
Requires-Dist: sphinx >=4 ; extra == "doc"
Requires-Dist: sphinxext-opengraph >= 0.5 ; extra == "doc"
Requires-Dist: furo ; extra == "doc"
Requires-Dist: numba ; extra == "numba"
Requires-Dist: pytest >= 6 ; extra == "test"
Requires-Dist: pytest-doctestplus ; extra == "test"
Requires-Dist: pytest-cov ; extra == "test"
Requires-Dist: pyyaml ; extra == "test"
Requires-Dist: toml ; extra == "test"
Requires-Dist: tensorflow >=2,<3 ; extra == "tf"
Requires-Dist: torch ; extra == "torch"
Project-URL: GitHub, https://github.com/lenskit/seedbank
Project-URL: Homepage, https://seedbank.lenksit.org
Provides-Extra: cuda11x
Provides-Extra: cupy
Provides-Extra: dev
Provides-Extra: doc
Provides-Extra: numba
Provides-Extra: test
Provides-Extra: tf
Provides-Extra: torch
